notiondbrs-0.1.1.dist-info/METADATA
notiondbrs-0.1.1.dist-info/WHEEL
notiondbrs/__init__.py
notiondbrs/notiondbrs.cpython-313-darwin.so
notiondbrs-0.1.1.dist-info/RECORD
