Metadata-Version: 2.4
Name: notiondbrs
Version: 0.1.1
Classifier: Programming Language :: Python :: 3
Classifier: License :: OSI Approved :: MIT License
Classifier: Operating System :: OS Independent
Classifier: Topic :: Software Development :: Libraries
Requires-Dist: python-dotenv>=1.1.1
Summary: A rust based python client for Notion's database
Keywords: notion,database,api,client
Author-email: Arjun <arjunprakash027@gmail.com>
License-Expression: MIT
Requires-Python: >=3.13
Project-URL: Homepage, https://github.com/arjunprakash027/notiondbrs
